Robot/RIE.py
Robot/ROM.py
Robot/UBI.py
Robot/__init__.py
RobotsInDeKlas_Controller-1.0.dist-info/METADATA
RobotsInDeKlas_Controller-1.0.dist-info/WHEEL
RobotsInDeKlas_Controller-1.0.dist-info/top_level.txt
RobotsInDeKlas_Controller-1.0.dist-info/RECORD
