Metadata-Version: 2.1
Name: RobotsInDeKlas-Controller
Version: 1.0
Summary: Bevat functies en classes gerelateerd aan de Robot, zie word document.
Home-page: https://github.com/007Whitetiger/RobotInDeKlas_Controller
Author: Pijn
Author-email: developer.whitetiger@gmail.com
License: MIT
Platform: UNKNOWN
Classifier: License :: OSI Approved :: MIT License
Classifier: Programming Language :: Python :: 3
Classifier: Programming Language :: Python :: 3.8
Requires-Dist: autobahn[serialization,twisted]
Requires-Dist: pyopenssl
